<!DOCTYPE ui:UiBinder SYSTEM "http://dl.google.com/gwt/DTD/xhtml.ent">
<ui:UiBinder xmlns:ui="urn:ui:com.google.gwt.uibinder"
	xmlns:g="urn:import:com.google.gwt.user.client.ui" xmlns:f="urn:import:org.zanata.webtrans.client">

	<ui:style field="style" type="org.zanata.webtrans.client.view.EditorOptionsView.Styles">
        .mainPanel {
			width:100%;
		}
		
		.mainPanel td {
			padding-bottom:10px;
		}
		
        .mainPanel table td {
            font-size: 13px;
            color: #FFFFFF;
        }

        .selectedPageSize {
            background-color: #B62918;
        }

        .pageSizeContainer {
            margin-left: 8px;
            margin-top: 8px;
        }

        .pageSizeContainer span {
            padding: 3px;
            border: 1px solid #808080;
            cursor: pointer;
            display: block;
            height: 15px;
            width: 15px;
            text-align: center;
            float: left;
            margin-right: 3px;
        }

    </ui:style>
	
	<g:VerticalPanel styleName="{style.mainPanel}">
		<g:cell>
			<g:VerticalPanel width="100%">
	            <g:Label ui:field="editorOptionHeader" styleName="gwt-sideMenu-header"/>
	            <g:CheckBox ui:field="editorButtonsChk"><ui:msg>Editor Buttons</ui:msg></g:CheckBox>
	            <g:CheckBox ui:field="enterChk"><ui:msg>'Enter' key saves immediately</ui:msg></g:CheckBox>
	            <g:CheckBox ui:field="useCodeMirrorChk" ><ui:msg>Use syntax highlighting Editor</ui:msg></g:CheckBox>
	            <g:CheckBox ui:field="showSaveApprovedWarningChk" ><ui:msg>Show 'Save as Approved' warning</ui:msg></g:CheckBox>
	            <g:CheckBox ui:field="spellCheckChk" ><ui:msg>Enable Spell Check</ui:msg></g:CheckBox>
	        </g:VerticalPanel>
        </g:cell>
        
        <g:cell>
        	<g:VerticalPanel width="100%">
        	 	<g:Label ui:field="navOptionHeader" styleName="gwt-sideMenu-header"/>
                <g:VerticalPanel ui:field="optionsContainer" />
            </g:VerticalPanel>
        </g:cell>

        <g:cell>
            <g:VerticalPanel width="100%">
                <g:Label ui:field="transMemoryHeader" styleName="gwt-sideMenu-header"/>
                <g:RadioButton name="transMemoryDisplayMode" ui:field="diffModeDiff" />
                <g:RadioButton name="transMemoryDisplayMode" ui:field="diffModeHighlight" />
            </g:VerticalPanel>
        </g:cell>


        
        <g:cell>
        	<g:VerticalPanel width="100%">
                <g:Label ui:field="pageSizeHeader" styleName="gwt-sideMenu-header"/>
                <g:HTMLPanel styleName="{style.pageSizeContainer}">
                    <g:InlineLabel ui:field="five" >5</g:InlineLabel>
                    <g:InlineLabel ui:field="ten" >10</g:InlineLabel>
                    <g:InlineLabel ui:field="twentyFive" >25</g:InlineLabel>
                    <g:InlineLabel ui:field="fifty" >50</g:InlineLabel>
                </g:HTMLPanel>
            </g:VerticalPanel>
        </g:cell>

        <g:cell>
            <g:VerticalPanel width="100%">
                <g:Label ui:field="displayHeader" styleName="gwt-sideMenu-header"/>
                <g:CheckBox ui:field="showTMChk" />
                <g:CheckBox ui:field="showGlossaryChk" />
                <g:CheckBox ui:field="showOptionalTransUnitDetailsChk" />
                <g:CheckBox ui:field="enableReferenceForSourceLang" />
            </g:VerticalPanel>
        </g:cell>
	                
	</g:VerticalPanel>
   

</ui:UiBinder> 